docop_tasks_restricted/__init__.py
docop_tasks_restricted/webhtml/__init__.py
docop_tasks_restricted/webhtml/html2text.py
docop_tasks_restricted-0.3.3.dist-info/LICENSE
docop_tasks_restricted-0.3.3.dist-info/METADATA
docop_tasks_restricted-0.3.3.dist-info/WHEEL
docop_tasks_restricted-0.3.3.dist-info/entry_points.txt
docop_tasks_restricted-0.3.3.dist-info/top_level.txt
docop_tasks_restricted-0.3.3.dist-info/RECORD
