Metadata-Version: 2.1
Name: docop-tasks-restricted
Version: 0.3.3
Summary: Tasks for docop that have more restrictive open source licensing
Author-email: Petri Savolainen <petri@koodaamo.fi>
License: GPLv3+
Project-URL: Homepage, https://github.com/koodaamo/docop-tasks-restricted
Project-URL: Repository, https://github.com/koodaamo/docop-tasks-restricted
Classifier: Programming Language :: Python :: 3
Classifier: Programming Language :: Python :: 3.10
Classifier: Programming Language :: Python :: 3.11
Classifier: Programming Language :: Python :: 3.12
Classifier: License :: OSI Approved :: GNU General Public License v3 or later (GPLv3+)
Requires-Python: >=3.10
License-File: LICENSE
Requires-Dist: trafilatura >=1.6.4
